devtools_json_viewer/__init__.py
devtools_json_viewer-1.0.1.dist-info/METADATA
devtools_json_viewer-1.0.1.dist-info/WHEEL
devtools_json_viewer-1.0.1.dist-info/top_level.txt
devtools_json_viewer-1.0.1.dist-info/RECORD
