Metadata-Version: 2.1
Name: devtools-json-viewer
Version: 1.0.1
Summary: JSON tree viewer
Home-page: https://devtools.at/tools/json-viewer
Author: DevTools.at
Author-email: hello@devtools.at
Project-URL: Homepage, https://devtools.at/tools/json-viewer
Project-URL: Repository, https://github.com/devtools-at/json-viewer
Classifier: Development Status :: 4 - Beta
Classifier: Intended Audience :: Developers
Classifier: License :: OSI Approved :: MIT License
Classifier: Programming Language :: Python :: 3
Requires-Python: >=3.8
